{
    "imageHeight": 857,
    "imageWidth": 724,
    "shapes": [
        {
            "label": "Poligon 31",
            "points": [
                [
                    315,
                    8
                ],
                [
                    302,
                    59
                ],
                [
                    293,
                    113
                ],
                [
                    289,
                    136
                ],
                [
                    278,
                    175
                ],
                [
                    258,
                    211
                ],
                [
                    246,
                    240
                ],
                [
                    240,
                    278
                ],
                [
                    230,
                    312
                ],
                [
                    221,
                    339
                ],
                [
                    213,
                    372
                ],
                [
                    210,
                    411
                ],
                [
                    212,
                    451
                ],
                [
                    217,
                    480
                ],
                [
                    217,
                    522
                ],
                [
                    221,
                    568
                ],
                [
                    230,
                    601
                ],
                [
                    254,
                    662
                ],
                [
                    277,
                    712
                ],
                [
                    292,
                    723
                ],
                [
                    374,
                    733
                ],
                [
                    408,
                    735
                ],
                [
                    462,
                    746
                ],
                [
                    521,
                    770
                ],
                [
                    535,
                    785
                ],
                [
                    586,
                    782
                ],
                [
                    581,
                    758
                ],
                [
                    530,
                    720
                ],
                [
                    492,
                    700
                ],
                [
                    454,
                    687
                ],
                [
                    419,
                    672
                ],
                [
                    366,
                    642
                ],
                [
                    361,
                    633
                ],
                [
                    346,
                    581
                ],
                [
                    341,
                    552
                ],
                [
                    333,
                    486
                ],
                [
                    335,
                    462
                ],
                [
                    336,
                    427
                ],
                [
                    337,
                    382
                ],
                [
                    344,
                    343
                ],
                [
                    352,
                    301
                ],
                [
                    360,
                    263
                ],
                [
                    371,
                    226
                ],
                [
                    385,
                    177
                ],
                [
                    398,
                    134
                ],
                [
                    407,
                    88
                ],
                [
                    417,
                    58
                ],
                [
                    421,
                    26
                ],
                [
                    421,
                    11
                ],
                [
                    420,
                    1
                ],
                [
                    313,
                    5
                ]
            ]
        }
    ]
}